LICENSE.txt
MANIFEST.in
README.md
requirements.txt
requirements_testing.txt
setup.cfg
setup.py
mecons/__init__.py
mecons/_version.py
mecons.egg-info/PKG-INFO
mecons.egg-info/SOURCES.txt
mecons.egg-info/dependency_links.txt
mecons.egg-info/not-zip-safe
mecons.egg-info/requires.txt
mecons.egg-info/top_level.txt
mecons/complexity/__init__.py
mecons/complexity/compressibility.py
mecons/complexity/entropy.py
mecons/complexity/tests/__init__.py
mecons/complexity/tests/test_compressibility.py
mecons/complexity/tests/test_entropy.py
mecons/utils/__init__.py
mecons/utils/binary.py
mecons/utils/preprocessing.py
mecons/utils/tests/__init__.py
mecons/utils/tests/test_binary.py
mecons/utils/tests/test_preprocessing.py