Metadata-Version: 2.1
Name: mecons
Version: 0.0.3
Summary: MeCons project for measuring consciousness.
Home-page: https://github.com/chrisferreyra13/mecons-py
Download-URL: https://github.com/chrisferreyra13/mecons-py
Maintainer: Christian Ferreyra
Maintainer-email: chrisferreyra13@gmail.com
License: BSD-3-Clause
Project-URL: Source, https://github.com/chrisferreyra13/mecons-py
Project-URL: Tracker, https://github.com/chrisferreyra13/mecons-py/issues/
Keywords: consciousness neuroscience neuroimaging MEG EEG brain
Platform: any
Classifier: Intended Audience :: Science/Research
Classifier: Intended Audience :: Developers
Classifier: License :: OSI Approved :: BSD License
Classifier: Programming Language :: Python
Classifier: Topic :: Software Development
Classifier: Topic :: Scientific/Engineering
Classifier: Topic :: Scientific/Engineering :: Human Machine Interfaces
Classifier: Operating System :: Microsoft :: Windows
Classifier: Operating System :: POSIX
Classifier: Operating System :: Unix
Classifier: Operating System :: MacOS
Classifier: Programming Language :: Python :: 3
Requires-Python: >=3.7
Provides-Extra: test
License-File: LICENSE.txt
